{
    "1" : [
        {"description" : "Insert desc", "price" : "100" , "name" : "piano"}
    ],
    "2" : [
        {"description" : "Insert desc", "price" : "100" , "name" : "Insert name"}
    ],
    "3" : [
        {"description" : "Insert desc", "price" : "100" , "name" : "Insert name"}
    ],
    "4" : [
        {"description" : "Insert desc", "price" : "100" , "name" : "Insert name"}
    ],
    "5" : [
        {"description" : "Insert desc", "price" : "100" , "name" : "Insert name"}
    ],
    "6" : [
        {"description" : "Insert desc", "price" : "100" , "name" : "Insert name"}
    ],
    "7" : [
        {"description" : "Insert desc", "price" : "100" , "name" : "Insert name"}
    ],
    "8" : [
        {"description" : "Insert desc", "price" : "100" , "name" : "Insert name"}
    ],
    "9" : [
        {"description" : "Insert desc", "price" : "100" , "name" : "Insert name"}
    ],
    "10" : [
        {"description" : "Insert desc", "price" : "100" , "name" : "Insert name"}
    ],
    "11" : [
        {"description" : "Insert desc", "price" : "100" , "name" : "Insert name"}
    ],
    "12" : [
        {"description" : "Insert desc", "price" : "100" , "name" : "Insert name"}
    ],
    "13" : [
        {"description" : "Insert desc", "price" : "100" , "name" : "Insert name"}
    ],
    "14" : [
        {"description" : "Insert desc", "price" : "100" , "name" : "Insert name"}
    ],
    "15" : [
        {"description" : "Insert desc", "price" : "100" , "name" : "Insert name"}
    ],
    "16" : [
        {"description" : "Insert desc", "price" : "100" , "name" : "Insert name"}
    ],
    "17" : [
        {"description" : "Insert desc", "price" : "100" , "name" : "Insert name"}
    ],
    "18" : [
        {"description" : "Insert desc", "price" : "100" , "name" : "Insert name"}
    ],
    "19" : [
        {"description" : "Insert desc", "price" : "100" , "name" : "Insert name"}
    ]
}